jay.py
jay-0.2.0.dist-info/DESCRIPTION.rst
jay-0.2.0.dist-info/entry_points.txt
jay-0.2.0.dist-info/METADATA
jay-0.2.0.dist-info/metadata.json
jay-0.2.0.dist-info/RECORD
jay-0.2.0.dist-info/top_level.txt
jay-0.2.0.dist-info/WHEEL
