Metadata-Version: 2.0
Name: jay
Version: 0.2.0
Summary: Command line tool to check and ssh into AWS EC2 instances
Home-page: https://github.com/colorstain/jay
Author: colorstain
Author-email: colostain+jay@gmail.com
License: MIT
Platform: UNKNOWN
Classifier: Development Status :: 3 - Alpha
Classifier: Intended Audience :: Developers
Requires-Dist: Click
Requires-Dist: boto3
